{
    "\\": 79525821,
    "b": 25170063,
    "e": 131496456,
    "g": 24899477,
    "i": 91464516,
    "n": 79422773,
    "{": 41704484,
    "d": 37137693,
    "o": 74076987,
    "c": 38746052,
    "u": 28875170,
    "m": 38719293,
    "t": 100409588,
    "}": 41674644,
    "\n": 30088702,
    "a": 93209806,
    "s": 62782483,
    "r": 65637841,
    "W": 1775071,
    " ": 225413219,
    "h": 46190355,
    "l": 51287174,
    ",": 21555463,
    "G": 2365028,
    "f": 32143347,
    "$": 41403341,
    "Z": 851651,
    "^": 12208745,
    "w": 13117993,
    "v": 12310985,
    "x": 9640442,
    "y": 14089399,
    "B": 2684625,
    "p": 29680055,
    ".": 13185737,
    "-": 11083908,
    "0": 7954853,
    "I": 3126434,
    "q": 9266315,
    "5": 1702076,
    "T": 5438410,
    "k": 6704059,
    "M": 2382542,
    ";": 1351970,
    "j": 2901405,
    "[": 3192549,
    "2": 10019313,
    "]": 3164808,
    "P": 2952130,
    "6": 1110955,
    "K": 1296768,
    "3": 2999506,
    "1": 13747732,
    "9": 884823,
    "A": 3466915,
    "7": 880877,
    "8": 907662,
    "4": 2044518,
    "E": 2247041,
    "=": 6993290,
    "_": 25825286,
    "(": 18361366,
    ")": 18439339,
    "D": 2266461,
    ":": 3837938,
    "H": 2163503,
    "V": 1285827,
    "R": 2651927,
    "+": 4706459,
    "F": 2586972,
    "O": 1472779,
    "'": 2183653,
    "S": 3795788,
    "\"": 399515,
    ">": 944116,
    "~": 1212598,
    "L": 3631331,
    "C": 3101470,
    "z": 2809880,
    "U": 1070462,
    "J": 563004,
    "N": 2370484,
    "|": 3682628,
    "*": 1937778,
    "&": 3246164,
    "<": 897264,
    "/": 1312859,
    "?": 165867,
    "!": 414251,
    "Q": 834231,
    "X": 1903292,
    "Y": 835308,
    "\u0301": 320,
    "@": 143271,
    "%": 32495,
    "\u00fc": 1049,
    "\u00df": 199,
    "\u00f6": 3575,
    "\u00f4": 411,
    "#": 128297,
    "\u201c": 2169,
    "`": 244176,
    "\u2192": 4179,
    "\u201d": 2173,
    "\u2019": 6768,
    "\r": 2721,
    "\u00e9": 6605,
    "\t": 2408069,
    "\u00b0": 841,
    "\u21d4": 57,
    "\u03c3": 869,
    "\u2265": 969,
    "\u0127": 39,
    "\u00d7": 1535,
    "\u2212": 3655,
    "\u03bc": 1376,
    "\u2248": 108,
    "\u2610": 1,
    "\u200b": 221,
    "\u00f3": 438,
    "\u00ed": 380,
    "\u00e8": 860,
    "\u00e0": 940,
    "\u010d": 26,
    "\u2014": 1072,
    "\u2264": 2261,
    "\u03b1": 6351,
    "\u03b8": 659,
    "\u00b7": 953,
    "\u00b1": 241,
    "\u2208": 2241,
    "\u2013": 3298,
    "\u27e8": 2515,
    "\u27e9": 2542,
    "\u27f6": 512,
    "\u03a0": 209,
    "\u2286": 430,
    "\u2209": 63,
    "\u0096": 74,
    "\u0394": 358,
    "\u03bd": 140,
    "\u03c1": 351,
    "\u0393": 445,
    "\u2190": 1293,
    "\u03b4": 705,
    "\u222a": 351,
    "\u2260": 530,
    "\u4e2d": 82,
    "\u56fd": 1,
    "\u00d6": 10,
    "\u00c9": 119,
    "\u00e4": 1334,
    "\u00f1": 173,
    "\u00e1": 729,
    "\u221e": 646,
    "\u21a5": 32,
    "\u03b2": 1939,
    "\u2243": 248,
    "\u2245": 155,
    "\u2964": 382,
    "\u03bb": 4487,
    "\u224c": 24,
    "\u22d9": 218,
    "\u22a3": 69,
    "\u2218": 267,
    "\u03c6": 1216,
    "\u223c": 82,
    "\u2032": 396,
    "\u0171": 4,
    "\u1e55": 1,
    "\u2044": 80,
    "\u25e6": 38,
    "\u0456": 10,
    "\u2022": 839,
    "\u2018": 508,
    "\u0151": 196,
    "\u2295": 73,
    "\ufffd": 131,
    "\u00a7": 661,
    "\u03c9": 351,
    "\u03c8": 211,
    "\u2203": 576,
    "\u0308": 60,
    "\u00c1": 38,
    "\u03a9": 202,
    "\u03c0": 1298,
    "\u011b": 20,
    "\u03b7": 81,
    "\u0142": 63,
    "\u2282": 131,
    "\u21d2": 187,
    "\u2229": 627,
    "\u03b5": 862,
    "\u00fa": 72,
    "\u00a3": 138,
    "\u00e3": 134,
    "\u00d8": 48,
    "\u008f": 28,
    "\u0081": 110,
    "\u0080": 18,
    "\u03c7": 27,
    "\u05bf": 4,
    "\u03b6": 31,
    "\u00ca": 1157,
    "\u03b3": 641,
    "\u0395": 5,
    "\u2217": 211,
    "\u00ef": 335,
    "\u201e": 24,
    "\u00a1": 169,
    "\u0304": 95,
    "\u221a": 182,
    "\u010c": 93,
    "\u2200": 1614,
    "\u2194": 591,
    "\u2205": 135,
    "\u2227": 691,
    "\u03ad": 4,
    "\u03be": 81,
    "\u03a3": 238,
    "\u2202": 661,
    "\u0103": 10,
    "\u0094": 17,
    "\u00e2": 160,
    "\u00a5": 13,
    "\u2228": 297,
    "\u0159": 37,
    "\u00ac": 676,
    "\u22ef": 52,
    "\u2206": 34,
    "\u0107": 53,
    "\u2193": 19,
    "\u200e": 1676,
    "\u228a": 5,
    "\u00f7": 86,
    "\u00c0": 9,
    "\u00eb": 192,
    "\u00e5": 252,
    "\u00ea": 178,
    "\u00f0": 143,
    "\u00d2": 98,
    "\u00ee": 211,
    "\u00ec": 66,
    "\u00d1": 27,
    "\u00f2": 118,
    "\u00ce": 16,
    "\u00cf": 8,
    "\u00c7": 11,
    "\u00e7": 222,
    "\u00fb": 39,
    "\u2223": 141,
    "\u00ad": 50,
    "\u039f": 3,
    "\u2061": 29,
    "\u03c4": 354,
    "\u2283": 88,
    "\u00f8": 98,
    "\u0161": 54,
    "\u0105": 17,
    "\u2287": 7,
    "\u22a2": 169,
    "\u00a6": 24,
    "\u00cb": 7,
    "\u00e6": 51,
    "\u00fe": 25,
    "\u2207": 198,
    "\u05b9": 1,
    "\u00ab": 93,
    "\u00bb": 95,
    "\u2554": 2,
    "\u2550": 201,
    "\u2566": 1,
    "\u2557": 2,
    "\u2551": 30,
    "\u2560": 5,
    "\u256c": 5,
    "\u2563": 5,
    "\u255a": 2,
    "\u2569": 1,
    "\u255d": 2,
    "\u3016": 3,
    "\u2225": 620,
    "\u21d1": 18,
    "\u2983": 41,
    "\u2984": 41,
    "\u2191": 525,
    "\u220f": 60,
    "\u2211": 253,
    "\u3002": 195,
    "\u226b": 518,
    "\u03b9": 1068,
    "\u226a": 52,
    "\u22a5": 157,
    "\u22a4": 119,
    "\u20ac": 70,
    "\u22c3": 73,
    "\u0437": 32,
    "\u0089": 10,
    "\u2236": 12,
    "\u25a1": 36,
    "\u2039": 47,
    "\u203a": 46,
    "\u25b8": 83,
    "\u22c2": 44,
    "\u2294": 26,
    "\u2293": 12,
    "\f": 12,
    "\u0422": 6,
    "\u0430": 121,
    "\u0440": 67,
    "\u0441": 98,
    "\u0438": 138,
    "\u043a": 48,
    "\u041c": 4,
    "\u043e": 149,
    "\u043b": 62,
    "\u0431": 20,
    "\u0448": 6,
    "\u03a6": 109,
    "\u0092": 88,
    "\u00b6": 11,
    "\u27fa": 4,
    "\u00a4": 31,
    "\u015b": 32,
    "\u2a2f": 13,
    "\u21a6": 33,
    "\u2a06": 39,
    "\u2a05": 24,
    "\u0160": 23,
    "\u2297": 98,
    "\u03a4": 4,
    "\u00fd": 58,
    "\u00bf": 49,
    "\u017c": 12,
    "\u0144": 80,
    "\u22c5": 161,
    "\u220e": 5,
    "\u6e15": 1,
    "\u91ce": 1,
    "\u660c": 1,
    "\u9152": 1,
    "\u4e95": 1,
    "\u62d3": 1,
    "\u53f2": 1,
    "\u2216": 5,
    "\u0444": 12,
    "\u00c4": 26,
    "\u2261": 297,
    "\u0219": 1,
    "\u0192": 18,
    "\u03ba": 54,
    "\u00dc": 36,
    "\u0327": 9,
    "\u0093": 25,
    "\u00a9": 30,
    "\u00d4": 18,
    "\u00d5": 51,
    "\u02c8": 3,
    "\u028a": 3,
    "\u0254": 3,
    "\u026a": 11,
    "\u0252": 1,
    "\u0097": 17,
    "\u2010": 36,
    "\u2736": 2,
    "\u2237": 1,
    "\u25bb": 2,
    "\u22c6": 10,
    "\u00d3": 96,
    "\u22a8": 17,
    "\u22c1": 2,
    "\u008e": 146,
    "\u015a": 3,
    "\u2254": 8,
    "\u2423": 18,
    "\u21aa": 18,
    "\u2020": 42,
    "\u227a": 13,
    "\u25cb": 1,
    "\u2195": 3,
    "\u0141": 43,
    "\u200c": 11,
    "\u2267": 3,
    "\u222b": 236,
    "\u203d": 1,
    "\u0117": 2,
    "\u011f": 4,
    "\u0292": 1,
    "\u25fb": 8,
    "\u25ca": 3,
    "\u00d0": 23,
    "\u008d": 8,
    "\u0398": 26,
    "\u2012": 1,
    "\u00cc": 22,
    "\u2733": 5,
    "\u039b": 93,
    "\u2933": 1,
    "\u2a56": 5,
    "\u0091": 17,
    "\u25ba": 5,
    "\u00ae": 25,
    "\u2220": 79,
    "\u0131": 11,
    "\u2060": 4,
    "\u0099": 18,
    "\u0088": 16,
    "\u2198": 5,
    "\u1eb9": 1,
    "\u013e": 2,
    "\u0303": 21,
    "\u02c6": 11,
    "\u03c5": 3,
    "\u03bf": 7,
    "\u03af": 3,
    "\ufeff": 5,
    "\u05d0": 17,
    "\u2197": 4,
    "\u2016": 19,
    "\u2219": 45,
    "\u015f": 6,
    "\u200f": 8,
    "\u0300": 3,
    "\u2271": 1,
    "\u0086": 12,
    "\u0087": 4,
    "\u0085": 11,
    "\u0084": 7,
    "\u25b5": 5,
    "\u0391": 5,
    "\u0428": 12,
    "\u22b8": 9,
    "\u214b": 21,
    "\u27f9": 14,
    "\u22bb": 1,
    "\u0119": 20,
    "\u25a2": 1,
    "\u0106": 1,
    "\u03a5": 6,
    "\u03a1": 5,
    "\u0397": 3,
    "\u039a": 1,
    "\u00de": 9,
    "\u009f": 12,
    "\u03cc": 1,
    "\u03c2": 3,
    "\u042d": 2,
    "\u0435": 148,
    "\u043c": 63,
    "\u043d": 105,
    "\u0442": 105,
    "\u044b": 27,
    "\u0443": 56,
    "\u0446": 10,
    "\u0439": 21,
    "\u044c": 24,
    "\u0433": 26,
    "\u3001": 30,
    "\u1e26": 1,
    "\u00cd": 11,
    "\u2a0f": 6,
    "\u2a0d": 1,
    "\u22c0": 1,
    "\u5f20": 7,
    "\u666f": 1,
    "\u5ba3": 1,
    "\u014d": 9,
    "\u0413": 15,
    "\u043f": 34,
    "\u0434": 50,
    "\u041b": 3,
    "\u00db": 2,
    "\u0336": 87,
    "\u0648": 2,
    "\u039e": 1,
    "\u25b3": 42,
    "\u9053": 4,
    "\u8001": 3,
    "\u5b50": 13,
    "\u7269": 3,
    "\u4ee5": 83,
    "\u7a00": 1,
    "\u70ba": 1,
    "\u8cb4": 1,
    "\u5927": 12,
    "\u6d77": 1,
    "\u6488": 1,
    "\u91dd": 1,
    "\u221d": 5,
    "\u230a": 30,
    "\u230b": 27,
    "\u0152": 2,
    "\u008c": 13,
    "\u21c4": 2,
    "\u017d": 2,
    "\u3008": 22,
    "\u3009": 22,
    "\u202a": 3,
    "\u00c2": 26,
    "\u29f8": 80,
    "\udbff\udce8": 3,
    "\u301c": 1,
    "\u041f": 10,
    "\u0447": 26,
    "\u0432": 55,
    "\u044e": 10,
    "\u0449": 11,
    "\u0412": 7,
    "\u044d": 7,
    "\u041a": 5,
    "\u0445": 18,
    "\u044f": 19,
    "\u0436": 8,
    "\u0421": 9,
    "\u060c": 2,
    "\u2028": 8,
    "\u0098": 12,
    "\u1f24": 1,
    "\u0399": 4,
    "\u00c8": 16,
    "\u0307": 5,
    "\u2b21": 1,
    "\u0418": 9,
    "\u0463": 8,
    "\u0424": 1,
    "\u0420": 4,
    "\u044a": 9,
    "\u0417": 1,
    "\u0410": 5,
    "\u041d": 3,
    "\u041e": 3,
    "\u0473": 1,
    "\u02bb": 2,
    "\u578b": 12,
    "\u306e": 17,
    "\u30a2": 2,
    "\u30d5": 5,
    "\u30a1": 1,
    "\u30a4": 5,
    "\u30f3": 3,
    "\u30fb": 12,
    "\u30ab": 1,
    "\u30c3": 1,
    "\u30c4": 1,
    "\u30e0": 1,
    "\u30fc": 16,
    "\u30c7": 1,
    "\u30a3": 1,
    "\u30ea": 8,
    "\u74b0": 1,
    "\u306b": 9,
    "\u304a": 2,
    "\u3051": 4,
    "\u308b": 18,
    "\u5e7e": 1,
    "\u4f55": 5,
    "\u5b66": 25,
    "\u7684": 465,
    "\u4f50": 1,
    "\u6b66": 1,
    "\u5bfe": 1,
    "\u5fdc": 1,
    "\u5cf6": 1,
    "\u5553": 1,
    "\u2a7f": 2,
    "\u22d6": 8,
    "\u25cf": 7,
    "\u2a02": 3,
    "\u2a01": 6,
    "\u2609": 2,
    "\u0155": 1,
    "\u018e": 4,
    "\u25fc": 6,
    "\u0415": 3,
    "\u0305": 18,
    "\u00dd": 2,
    "\u3010": 1,
    "\u3011": 1,
    "\u009c": 3,
    "\u00f9": 33,
    "\u0130": 10,
    "\u0323": 5,
    "\u009d": 8,
    "\u00c3": 43,
    "\u0095": 9,
    "\u2021": 3,
    "\u00a2": 48,
    "\u1fb0": 64,
    "\udbff\udc18": 2,
    "\u2605": 7,
    "\u200d": 24,
    "\u220b": 2,
    "\u227e": 3,
    "\u203b": 2,
    "\u223d": 1,
    "\u2029": 2,
    "\u21bb": 4,
    "\u22ca": 62,
    "\u030a": 7,
    "\u201a": 8,
    "\u3017": 2,
    "\u012d": 7,
    "\u00ff": 39,
    "\u008a": 48,
    "\u0083": 15,
    "\u03a8": 24,
    "\u222e": 10,
    "\u2030": 4,
    "\u22bf": 1,
    "\u009a": 33,
    "\u266f": 6,
    "\u22a6": 1,
    "\ua714": 1,
    "\u251c": 1,
    "\u1161": 1,
    "\u0370": 1,
    "\u0371": 1,
    "\u2c75": 1,
    "\u2c76": 1,
    "\u23ac": 1,
    "\u2800": 26,
    "\u2666": 5,
    "\u23af": 39,
    "\u0082": 195,
    "\u00c5": 27,
    "\u2714": 2,
    "\ufe0f": 3,
    "\u009e": 4,
    "\u2224": 7,
    "\u22ac": 5,
    "\u22a0": 1,
    "\u0306": 1,
    "\u9023": 1,
    "\u7d9a": 1,
    "\u7fa4": 2,
    "\u8ad6": 3,
    "\u4ee3": 14,
    "\u6570": 109,
    "\u2234": 10,
    "\u1d27": 1,
    "\u263a": 3,
    "\u56fe": 12,
    "\u0423": 2,
    "\u2b1d": 138,
    "\u1ec5": 1,
    "\u0110": 1,
    "\u1eb7": 1,
    "\u0125": 4,
    "\u00c6": 9,
    "\u008b": 3,
    "\u0090": 8,
    "\u2663": 9,
    "\u2660": 6,
    "\u2662": 3,
    "\u2661": 6,
    "\u25c6": 2,
    "\u00f5": 7,
    "\u2031": 1,
    "\u2210": 3,
    "\udbff\udc01": 1,
    "\u2015": 9,
    "\u21e8": 1,
    "\u017e": 10,
    "\u0411": 1,
    "\u0414": 2,
    "\u0416": 1,
    "\u2715": 1,
    "\u21d0": 8,
    "\u6c38": 1,
    "\u7530": 2,
    "\u5ca9": 1,
    "\u4e09": 3,
    "\u90ce": 1,
    "\u9075": 1,
    "\u9ce5": 1,
    "\u7fbd": 1,
    "\u6e90": 2,
    "\u5409": 1,
    "\u5b88": 6,
    "\u656c": 1,
    "\ufffc": 18,
    "\u2502": 7,
    "\u27ee": 17,
    "\u27ef": 17,
    "\u221b": 4,
    "\u0146": 3,
    "\u2045": 84,
    "\u2046": 84,
    "\u25fd": 2,
    "\u0251": 2,
    "\u2374": 6,
    "\udbff\udc2d": 2,
    "\udbff\udc70": 8,
    "\udbff\udc6e": 1,
    "\u02c7": 3,
    "\u019e": 1,
    "\u2284": 3,
    "\u27cb": 6,
    "\u27cd": 6,
    "\u0169": 3,
    "\u279c": 1,
    "\u2716": 3,
    "\u229e": 1,
    "\u738b": 1,
    "\u5f6c": 1,
    "\u65ed": 1,
    "\u017b": 2,
    "\u2266": 3,
    "\u22ee": 13,
    "\u2665": 7,
    "\u0148": 2,
    "\u5e72": 1,
    "\u652f": 2,
    "\u30b2": 1,
    "\u30b8": 1,
    "\u6298": 3,
    "\u7d19": 3,
    "\u65e5": 1,
    "\u672c": 13,
    "\u8a9e": 1,
    "\u898f": 1,
    "\u7bc4": 1,
    "\u647a": 1,
    "\u6587": 4,
    "\u7e41": 1,
    "\u9ad4": 1,
    "\u5b57": 2,
    "\u89c4": 1,
    "\u8303": 3,
    "\u7eb8": 1,
    "\u7b80": 16,
    "\u4f53": 24,
    "\u6238": 1,
    "\u683c": 18,
    "\u5c71": 1,
    "\u5d0e": 1,
    "\u96c5": 1,
    "\u4eba": 1,
    "\u25a0": 4,
    "\u20d7": 4,
    "\u23a1": 2,
    "\u23a4": 2,
    "\u23a3": 2,
    "\u23a6": 2,
    "\u015e": 3,
    "\u000f": 1,
    "\u00da": 4,
    "\u0302": 7,
    "\u25b2": 4,
    "\u30e9": 3,
    "\u30d9": 3,
    "\u30eb": 4,
    "\u6c6a": 1,
    "\u9554": 1,
    "\u3053": 7,
    "\u5c11": 2,
    "\u3057": 11,
    "\u8aac": 1,
    "\u660e": 8,
    "\u3068": 16,
    "\u308a": 3,
    "\u3042": 5,
    "\u3048": 2,
    "\u305a": 2,
    "\u66f8": 8,
    "\u3044": 14,
    "\u305f": 8,
    "\u3061": 4,
    "\u30de": 2,
    "\u30af": 4,
    "\u3067": 10,
    "\u3066": 23,
    "\u4e00": 50,
    "\u81f4": 2,
    "\u3059": 6,
    "\u4e8b": 4,
    "\u3092": 13,
    "\u793a": 33,
    "\u305d": 2,
    "\u3046": 8,
    "\u671b": 3,
    "\u6708": 1,
    "\u5148": 10,
    "\u751f": 9,
    "\u3082": 4,
    "\u5f15": 3,
    "\u7528": 70,
    "\u308c": 4,
    "\u304c": 9,
    "\u304d": 10,
    "\u3064": 2,
    "\u307e": 3,
    "\u8a08": 2,
    "\u7b97": 35,
    "\u4ecb": 8,
    "\u308d": 1,
    "\u30dd": 1,
    "\u30c8": 4,
    "\u3063": 17,
    "\u304b": 16,
    "\u304f": 8,
    "\u6bd4": 12,
    "\u8f03": 1,
    "\u8a18": 1,
    "\u53f7": 4,
    "\u3076": 1,
    "\u3083": 3,
    "\u306a": 4,
    "\u3069": 3,
    "\u3088": 2,
    "\u4f8b": 12,
    "\u4e0d": 61,
    "\u53ef": 76,
    "\u80fd": 18,
    "\u3060": 3,
    "\u3089": 4,
    "\u65b9": 150,
    "\u6cd5": 67,
    "\u53d6": 21,
    "\u30d0": 2,
    "\u30c9": 1,
    "\u7248": 3,
    "\u306d": 1,
    "\u30a8": 3,
    "\u884c": 28,
    "\u5b9f": 1,
    "\u306f": 9,
    "\u8a3c": 1,
    "\u5b9a": 19,
    "\u7fa9": 2,
    "\u3055": 1,
    "\u3058": 2,
    "\u3081": 2,
    "\u8a00": 2,
    "\u308f": 2,
    "\u3084": 2,
    "\u6b21": 5,
    "\u5143": 8,
    "\u5834": 3,
    "\u5408": 10,
    "\u4f7f": 55,
    "\u30cb": 1,
    "\u30df": 2,
    "\u30b9": 3,
    "\u4fee": 1,
    "\u6b63": 2,
    "\u5f79": 1,
    "\u5272": 1,
    "\u3054": 1,
    "\u30b1": 1,
    "\u5165": 14,
    "\u3093": 2,
    "\u30aa": 2,
    "\u307f": 1,
    "\u4e0b": 31,
    "\u4ed8": 1,
    "\u88ab": 2,
    "\u30b7": 1,
    "\u9055": 2,
    "\u3079": 1,
    "\u6b7b": 1,
    "\u591a": 9,
    "\u5206": 35,
    "\u7121": 1,
    "\u9650": 10,
    "\u9593": 1,
    "\u21cf": 1,
    "\u0451": 1,
    "\u30da": 1,
    "\u30d1": 1,
    "\u51fa": 33,
    "\u6027": 26,
    "\u8cea": 3,
    "\u5168": 12,
    "\u90e8": 10,
    "\u1f45": 3,
    "\u1f14": 3,
    "\u1fd6": 3,
    "\udbff\udc43": 1,
    "\udbff\udc3c": 1,
    "\u55bb": 1,
    "\u826f": 2,
    "\u0749": 1,
    "\u039c": 3,
    "\u05d7": 1,
    "\u2a3c": 2,
    "\u5f53": 21,
    "\u8b70": 1,
    "\u2a7d": 1,
    "\u2acb": 2,
    "\u0392": 2,
    "\u227c": 10,
    "\u2373": 5,
    "\u2395": 1,
    "\u2308": 5,
    "\u204e": 2,
    "\u0650": 1,
    "\uf0e0": 1,
    "\u252c": 1,
    "\u266b": 2,
    "\u2118": 3,
    "\u27e6": 10,
    "\u27e7": 10,
    "\u2500": 2,
    "\u263c": 2,
    "\u144c": 1,
    "\u144e": 1,
    "\u1455": 1,
    "\u2299": 1,
    "\u012f": 2,
    "\u2309": 3,
    "\u21f8": 1,
    "\u0190": 2,
    "\u0153": 2,
    "\u1e6d": 1,
    "\u064c": 2,
    "\u300c": 1,
    "\u300d": 1,
    "\u571f": 4,
    "\u219d": 2,
    "\u21af": 5,
    "\u6309": 3,
    "\u9879": 55,
    "\u5217": 5,
    "\u518d": 5,
    "\u7ec4": 13,
    "\u8d77": 3,
    "\u6765": 26,
    "\u6211": 132,
    "\u4eec": 129,
    "\u63d0": 8,
    "\u4e86": 51,
    "\u4e2a": 36,
    "\u636e": 49,
    "\u9a71": 5,
    "\u52a8": 12,
    "\u57fa": 8,
    "\u4e8e": 57,
    "\u795e": 44,
    "\u7ecf": 48,
    "\u4e60": 19,
    "\u5177": 17,
    "\u6709": 63,
    "\u548c": 59,
    "\u5728": 57,
    "\u5149": 5,
    "\u6ed1": 4,
    "\u95f4": 44,
    "\u65ad": 4,
    "\u96c6": 20,
    "\u4e0a": 37,
    "\u8fdb": 25,
    "\u6d4b": 22,
    "\u8bd5": 14,
    "\u8fd8": 6,
    "\u6fc0": 7,
    "\u6ce2": 6,
    "\u7ba1": 5,
    "\u95ee": 17,
    "\u9898": 18,
    "\u7ed3": 29,
    "\u6784": 18,
    "\u5c06": 15,
    "\u4f9b": 2,
    "\u6210": 12,
    "\u7801": 2,
    "\u4fbf": 1,
    "\u540c": 41,
    "\u5de5": 6,
    "\u4f5c": 13,
    "\u8f83": 10,
    "\u73bb": 5,
    "\u5c14": 5,
    "\u5179": 5,
    "\u66fc": 5,
    "\u7a0b": 88,
    "\u662f": 75,
    "\u6c14": 15,
    "\u7406": 12,
    "\u4e4e": 1,
    "\u529b": 8,
    "\u4e4b": 13,
    "\u79cd": 16,
    "\u6a21": 17,
    "\u901a": 25,
    "\u8fc7": 27,
    "\u7edf": 11,
    "\u8ba1": 31,
    "\u624b": 1,
    "\u6bb5": 6,
    "\u5fae": 5,
    "\u89c2": 3,
    "\u7c92": 5,
    "\u8fd0": 3,
    "\u72b6": 5,
    "\u6001": 5,
    "\u8868": 35,
    "\u8ff0": 4,
    "\u4e3a": 62,
    "\u5173": 13,
    "\u7a7a": 11,
    "\u901f": 20,
    "\u5ea6": 46,
    "\u8fde": 6,
    "\u7eed": 1,
    "\u5e03": 5,
    "\u51fd": 18,
    "\u7ed9": 13,
    "\u65f6": 60,
    "\u6f14": 19,
    "\u5316": 34,
    "\u63cf": 2,
    "\u53ea": 12,
    "\u66f4": 8,
    "\u6539": 1,
    "\u76f8": 23,
    "\u4e92": 3,
    "\u5efa": 2,
    "\u5176": 41,
    "\u4ed6": 5,
    "\u7c7b": 7,
    "\u5982": 27,
    "\u5bf9": 63,
    "\u5e26": 6,
    "\u7535": 3,
    "\u9700": 15,
    "\u8981": 21,
    "\u8003": 9,
    "\u8651": 9,
    "\u8377": 1,
    "\u53ca": 8,
    "\u78c1": 1,
    "\u573a": 1,
    "\u7b49": 10,
    "\u6b64": 5,
    "\u5e94": 22,
    "\u6216": 6,
    "\u63a7": 1,
    "\u6838": 2,
    "\u805a": 1,
    "\u53d8": 21,
    "\u8f93": 12,
    "\u8f90": 1,
    "\u5c04": 1,
    "\u5f62": 19,
    "\u4f17": 1,
    "\u9886": 1,
    "\u57df": 7,
    "\u90fd": 11,
    "\u5e7f": 3,
    "\u6cdb": 3,
    "\u53f3": 5,
    "\u7aef": 5,
    "\u78b0": 49,
    "\u649e": 49,
    "\u5305": 4,
    "\u542b": 9,
    "\u9ad8": 5,
    "\u7ef4": 11,
    "\u503c": 38,
    "\u79ef": 14,
    "\u5f88": 4,
    "\u91cf": 29,
    "\u7cfb": 18,
    "\u964d": 3,
    "\u4f4e": 3,
    "\u96be": 5,
    "\u4e9b": 9,
    "\u5b9e": 15,
    "\u9a8c": 9,
    "\u60c5": 6,
    "\u539f": 2,
    "\u59cb": 3,
    "\u903c": 9,
    "\u8fd1": 13,
    "\u597d": 8,
    "\u4f46": 13,
    "\u7531": 6,
    "\u5373": 20,
    "\u4f9d": 7,
    "\u7136": 10,
    "\u56f0": 1,
    "\u76f4": 6,
    "\u63a5": 15,
    "\u6c42": 21,
    "\u89e3": 27,
    "\u79bb": 10,
    "\u6563": 8,
    "\u91cd": 6,
    "\u65b0": 5,
    "\u83b7": 6,
    "\u5f97": 37,
    "\u4f3c": 5,
    "\u4e0e": 10,
    "\u5178": 1,
    "\u6d41": 15,
    "\u8fd9": 41,
    "\u540d": 1,
    "\u5c55": 21,
    "\u5f00": 5,
    "\u6240": 15,
    "\u77e9": 50,
    "\u8bf4": 8,
    "\u952e": 2,
    "\u5c31": 22,
    "\u5c01": 24,
    "\u95ed": 24,
    "\u9636": 14,
    "\u5230": 44,
    "\u6700": 9,
    "\u65e9": 1,
    "\u9009": 14,
    "\u5355": 17,
    "\u5f0f": 39,
    "\u8ba9": 1,
    "\u540e": 17,
    "\u8bba": 5,
    "\u8005": 9,
    "\u679c": 24,
    "\u6781": 3,
    "\u71b5": 1,
    "\u5c40": 11,
    "\u53cc": 3,
    "\u66f2": 3,
    "\u5219": 13,
    "\u968f": 5,
    "\u7740": 2,
    "\u6df1": 3,
    "\u6280": 3,
    "\u672f": 2,
    "\u53d1": 4,
    "\u907f": 1,
    "\u514d": 1,
    "\u707e": 1,
    "\u7cbe": 11,
    "\u786e": 9,
    "\u4e5f": 25,
    "\u5de8": 1,
    "\u4efb": 7,
    "\u52a1": 1,
    "\u7f51": 65,
    "\u7edc": 59,
    "\u62df": 4,
    "\u52a0": 2,
    "\u9762": 14,
    "\u5377": 10,
    "\u91ca": 1,
    "\u70ed": 1,
    "\u7a33": 2,
    "\u5df2": 6,
    "\u8bad": 23,
    "\u7ec3": 23,
    "\u7279": 8,
    "\u5f81": 5,
    "\u4f30": 6,
    "\u51c6": 2,
    "\u4e14": 4,
    "\u6b65": 6,
    "\u73b0": 10,
    "\u4f4d": 6,
    "\u7f6e": 2,
    "\u5bc6": 12,
    "\u6e29": 3,
    "\u5e73": 6,
    "\u8861": 1,
    "\u4e49": 7,
    "\u628a": 7,
    "\u5404": 10,
    "\u5411": 3,
    "\u6574": 5,
    "\u82e5": 1,
    "\u7d20": 3,
    "\u8d1f": 1,
    "\u7ea6": 1,
    "\u79f0": 7,
    "\u4fdd": 7,
    "\u7559": 4,
    "\u524d": 15,
    "\u6837": 23,
    "\u6ce8": 4,
    "\u610f": 8,
    "\u6ee1": 17,
    "\u8db3": 19,
    "\u672a": 2,
    "\u77e5": 5,
    "\u8bb0": 6,
    "\u5199": 3,
    "\u7ebf": 6,
    "\u88c2": 3,
    "\u4e24": 10,
    "\u5047": 5,
    "\u8bbe": 8,
    "\u90a3": 3,
    "\u4e48": 3,
    "\u6052": 5,
    "\u5b83": 2,
    "\u89c1": 3,
    "\u56e0": 10,
    "\u91c7": 13,
    "\u4ece": 14,
    "\u53c2": 6,
    "\u521d": 9,
    "\u8f68": 18,
    "\u8ff9": 18,
    "\u76ee": 2,
    "\u9002": 1,
    "\u56f4": 4,
    "\u5904": 14,
    "\u7ecd": 6,
    "\u4e3b": 4,
    "\u68af": 4,
    "\u6301": 1,
    "\u6b62": 2,
    "\u5730": 2,
    "\u590d": 2,
    "\u975e": 5,
    "\u5e38": 4,
    "\u822c": 3,
    "\u5fc3": 2,
    "\u522b": 11,
    "\u8eab": 3,
    "\u8d28": 8,
    "\u6846": 2,
    "\u692d": 2,
    "\u5706": 2,
    "\u66ff": 6,
    "\u5bfc": 4,
    "\u5e0c": 2,
    "\u5fc5": 2,
    "\u987b": 2,
    "\u5dee": 13,
    "\u67d0": 6,
    "\u7814": 1,
    "\u7a76": 1,
    "\u8bfb": 1,
    "\u91cc": 2,
    "\u4e8c": 6,
    "\u7b2c": 9,
    "\u8be5": 8,
    "\u5c3d": 6,
    "\u7b26": 3,
    "\u4f3d": 2,
    "\u5229": 4,
    "\u7565": 3,
    "\u523b": 9,
    "\u6761": 6,
    "\u79fb": 2,
    "\u65cb": 1,
    "\u8f6c": 4,
    "\u5f85": 4,
    "\u8ba4": 2,
    "\u6bcf": 6,
    "\u7167": 2,
    "\u5747": 9,
    "\u8bc1": 4,
    "\u76ca": 1,
    "\u4f18": 6,
    "\u4ef6": 3,
    "\u505a": 5,
    "\u9065": 1,
    "\u8fdc": 3,
    "\u533a": 7,
    "\u77ed": 2,
    "\u5185": 2,
    "\u5f71": 4,
    "\u54cd": 4,
    "\u51cf": 1,
    "\u53bb": 6,
    "\u4f1a": 7,
    "\u5931": 6,
    "\u4ea7": 2,
    "\u9645": 1,
    "\u5f3a": 2,
    "\u6362": 6,
    "\u4e22": 2,
    "\u4fe1": 6,
    "\u606f": 4,
    "\u51b5": 5,
    "\u8def": 1,
    "\u5750": 2,
    "\u6807": 3,
    "\u8f74": 3,
    "\u7ffb": 1,
    "\u4ee4": 2,
    "\u81ea": 4,
    "\u7eb2": 7,
    "\u6790": 8,
    "\u65e0": 3,
    "\u5bdf": 1,
    "\u62e9": 8,
    "\u5f1b": 1,
    "\u8c6b": 1,
    "\u770b": 3,
    "\u4ec5": 3,
    "\u5916": 2,
    "\u51b3": 1,
    "\u70b9": 6,
    "\u800c": 9,
    "\u9664": 1,
    "\u5de7": 1,
    "\u6ca1": 5,
    "\u663e": 3,
    "\u7ea7": 1,
    "\u8457": 1,
    "\u9884": 9,
    "\u4f59": 1,
    "\u5b58": 2,
    "\u50a8": 2,
    "\u751a": 2,
    "\u81f3": 6,
    "\u6742": 1,
    "\u5feb": 3,
    "\u591f": 2,
    "\u5e76": 10,
    "\u5f55": 1,
    "\u53d7": 3,
    "\u8fb9": 2,
    "\u903b": 1,
    "\u8f91": 1,
    "\u987a": 2,
    "\u5e8f": 2,
    "\u611f": 2,
    "\u89c9": 2,
    "\u9010": 2,
    "\u9012": 1,
    "\u5220": 1,
    "\u8bdd": 2,
    "\u5947": 1,
    "\u602a": 1,
    "\u6e05": 1,
    "\u695a": 1,
    "\u9519": 2,
    "\u56de": 3,
    "\u4ec0": 1,
    "\u4e1c": 1,
    "\u897f": 1,
    "\u60dc": 1,
    "\u5468": 2,
    "\u4e13": 1,
    "\u5236": 1,
    "\u9632": 1,
    "\u635f": 3,
    "\u673a": 1,
    "\u771f": 4,
    "\u5339": 1,
    "\u914d": 1,
    "\u8d44": 1,
    "\u7247": 2,
    "\u8ddd": 2,
    "\u957f": 3,
    "\u60f3": 1,
    "\u9996": 1,
    "\u675f": 1,
    "\u62e5": 1,
    "\u5b9c": 1,
    "\u8bc4": 2,
    "\u8bef": 8,
    "\u7840": 1,
    "\u53e6": 1,
    "\u5c3a": 2,
    "\u5bf8": 2,
    "\u6d3b": 1,
    "\u534a": 2,
    "\u900f": 1,
    "\u5de6": 4,
    "\u4fa7": 2,
    "\u6a2a": 1,
    "\u7eb5": 1,
    "\u9020": 5,
    "\u529f": 1,
    "\u5757": 2,
    "\u6548": 3,
    "\u72ec": 1,
    "\u8ba8": 1,
    "\u51e0": 1,
    "\u8574": 1,
    "\u4ef7": 2,
    "\u603b": 2,
    "\u5f8b": 1,
    "\u754c": 2,
    "\u8c31": 1,
    "\u5f84": 1,
    "\u8d56": 1,
    "\u624d": 1,
    "\u6839": 4,
    "\u5b8c": 1,
    "\u500d": 4,
    "\u56fa": 2,
    "\u9891": 2,
    "\u7387": 2,
    "\u589e": 1,
    "\u8bb2": 1,
    "\u5c0f": 1,
    "\u878d": 1,
    "\u5bb9": 1,
    "\u6613": 1,
    "\u63a8": 1,
    "\u9644": 1,
    "\u0233": 3,
    "\u21be": 2,
    "\u55ef": 1,
    "\u592a": 1,
    "\u677f": 2,
    "\u5389": 1,
    "\u5bb3": 1,
    "\u554a": 1,
    "\u5f04": 1,
    "\u601d": 1,
    "\u86cb": 1,
    "\u75bc": 1,
    "\u6982": 1,
    "\u5ff5": 1,
    "\u4f60": 2,
    "\u250a": 1,
    "\u2291": 4,
    "\u2292": 4,
    "\u2794": 1,
    "\u04aa": 1,
    "\u06af": 1,
    "\u0633": 1,
    "\u2288": 1,
    "\u220a": 4,
    "\u2588": 1,
    "\u1e91": 8,
    "\u03ac": 1,
    "\ua76b": 2,
    "\u2215": 1,
    "\u064e": 1,
    "\u2235": 1,
    "\u011e": 1,
    "\u021b": 1,
    "\u2238": 2,
    "\u273d": 2,
    "\u30fe": 1,
    "\u2027": 4
}